unittest_parametrize/__init__.py
unittest_parametrize/py.typed
unittest_parametrize-1.8.0.dist-info/licenses/LICENSE
unittest_parametrize-1.8.0.dist-info/METADATA
unittest_parametrize-1.8.0.dist-info/WHEEL
unittest_parametrize-1.8.0.dist-info/top_level.txt
unittest_parametrize-1.8.0.dist-info/RECORD
